boa/__init__.py
boa/boa_obj.py
boa/json.py
boa/yaml.py
PyBoa-1.3.8.dist-info/LICENSE
PyBoa-1.3.8.dist-info/METADATA
PyBoa-1.3.8.dist-info/WHEEL
PyBoa-1.3.8.dist-info/top_level.txt
PyBoa-1.3.8.dist-info/RECORD
