Metadata-Version: 2.1
Name: PyBoa
Version: 1.3.8
Summary: Subclass of list and dict, recursively, giving attribute access and helper functions
Home-page: https://github.com/Pythux/PyBoa
Author: Pythux
License: MIT
Platform: UNKNOWN
Classifier: Programming Language :: Python :: 3
Classifier: License :: OSI Approved :: MIT License
Classifier: Operating System :: OS Independent
Classifier: Intended Audience :: Developers
Requires-Python: >=3.6
